flimview/__init__.py
flimview/datasets.py
flimview/flim.py
flimview/io_utils.py
flimview/models.py
flimview/plot_utils.py
flimview/version.py
flimview-1.2.0.dist-info/METADATA
flimview-1.2.0.dist-info/WHEEL
flimview-1.2.0.dist-info/top_level.txt
flimview-1.2.0.dist-info/RECORD
