Metadata-Version: 2.1
Name: flimview
Version: 1.2.0
Summary: A software framework to handle, visualize and analyze FLIM data
Home-page: https://github.com/Biophotonics-COMI/flimview
Author: Matias Carrasco Kind & COMI Lab
Author-email: mcarras2@illinois.edu
License: License.txt
Platform: UNKNOWN
Requires-Dist: scipy
Requires-Dist: numpy
Requires-Dist: matplotlib
Requires-Dist: sdtfile
Requires-Dist: pandas
Requires-Dist: tqdm
Requires-Dist: h5py
Requires-Dist: Pillow
Requires-Dist: pooch
